qwiic_oled_base/__init__.py
qwiic_oled_base/oled_fonts.py
qwiic_oled_base/oled_logos.py
qwiic_oled_base/qwiic_oled_base.py
qwiic_oled_base/fonts/0_font5x7.bin
qwiic_oled_base/fonts/1_font8x16.bin
qwiic_oled_base/fonts/2_7segment.bin
qwiic_oled_base/fonts/3_fontlargenumber.bin
qwiic_oled_base/fonts/4_fontlargeletter31x48.bin
sparkfun_qwiic_oled_base-0.0.2.dist-info/LICENSE
sparkfun_qwiic_oled_base-0.0.2.dist-info/METADATA
sparkfun_qwiic_oled_base-0.0.2.dist-info/WHEEL
sparkfun_qwiic_oled_base-0.0.2.dist-info/top_level.txt
sparkfun_qwiic_oled_base-0.0.2.dist-info/RECORD
